[
	{
		"week": 1,
		"title": "Intro to iOS",
		"description": "This session will go over...",
		"image": "http://via.placeholder.com/550x350",
		"resources": {
			"code": "www.github.com",
			"slides": "www.drive.google.com",
			"screencast": null
		}
	},
	{
		"week": 2,
		"title": "Multiview Applications",
		"description": "This session will go over...",
		"image": "http://via.placeholder.com/550x350",
		"resources": {
			"code": "www.github.com",
			"slides": "www.drive.google.com",
			"screencast": null
		}
	}
]